bevy/__init__.py
bevy/factory_contextvars.py
bevy/injectors/__init__.py
bevy/injectors/classes.py
bevy/injectors/functions.py
bevy/options.py
bevy/provider_state.py
bevy/providers/__init__.py
bevy/providers/annotated_provider.py
bevy/providers/provider.py
bevy/providers/type_provider.py
bevy/repository.py
bevy-2.0.2.dist-info/LICENSE
bevy-2.0.2.dist-info/METADATA
bevy-2.0.2.dist-info/WHEEL
bevy-2.0.2.dist-info/RECORD
