Metadata-Version: 2.1
Name: Bevy
Version: 2.0.2
Summary: Python Dependency Injection made simple so you can focus on creating amazing code.
Home-page: https://github.com/ZechCodes/Bevy
License: MIT
Keywords: dependency,injection,annotations,types
Author: Zech Zimmerman
Author-email: hi@zech.codes
Requires-Python: >=3.10,<4.0
Classifier: License :: OSI Approved :: MIT License
Classifier: Programming Language :: Python :: 3
Classifier: Programming Language :: Python :: 3.10
Classifier: Programming Language :: Python :: 3.11
Classifier: Topic :: Software Development :: Libraries :: Application Frameworks
Project-URL: Documentation, https://github.com/ZechCodes/Bevy/blob/main/README.md
Project-URL: Repository, https://github.com/ZechCodes/Bevy
